LICENSE
MANIFEST.in
README.md
setup.cfg
setup.py
src/drbot/Botling.py
src/drbot/DrBot.py
src/drbot/Regi.py
src/drbot/Stream.py
src/drbot/__init__.py
src/drbot/log.py
src/drbot/reddit.py
src/drbot/root_defaults.json
src/drbot/settings.py
src/drbot/storage.py
src/drbot/util.py
src/drbot/botlings/AdminWatcher.py
src/drbot/botlings/AutoLocker.py
src/drbot/botlings/ModlogArchiver.py
src/drbot/botlings/ModmailLinker.py
src/drbot/botlings/Pointling.py
src/drbot/botlings/QueueAgeWatcher.py
src/drbot/botlings/QueueSizeWatcher.py
src/drbot/botlings/SelfModerationWatcher.py
src/drbot/botlings/SidebarSyncer.py
src/drbot/botlings/UserFlairGuard.py
src/drbot/botlings/UserFlairGuardPrototype.py
src/drbot/botlings/WeekdayFlairEnforcer.py
src/drbot/botlings/__init__.py
src/drbot/streams/BeforelessStream.py
src/drbot/streams/CommentStream.py
src/drbot/streams/EditedStream.py
src/drbot/streams/ModlogStream.py
src/drbot/streams/ModmailConversationStream.py
src/drbot/streams/ModmailMessageStream.py
src/drbot/streams/PostStream.py
src/drbot/streams/TimeDelayPostStream.py
src/drbot/streams/TimeGuardedStream.py
src/drbot/streams/__init__.py
src/drbot/streams/meta.py
src/drbot_reddit.egg-info/PKG-INFO
src/drbot_reddit.egg-info/SOURCES.txt
src/drbot_reddit.egg-info/dependency_links.txt
src/drbot_reddit.egg-info/requires.txt
src/drbot_reddit.egg-info/top_level.txt