Metadata-Version: 2.1
Name: drbot-reddit
Version: 2.0.6
Summary: DrBot - A modular Reddit bot to cure your moderation woes.
Home-page: https://github.com/c0d3rman/DrBot
Author: c0d3rman
License: CC BY-SA 4.0
Classifier: Development Status :: 3 - Alpha
Classifier: Intended Audience :: Developers
Classifier: License :: Free To Use But Restricted
Classifier: Natural Language :: English
Classifier: Programming Language :: Python
Classifier: Programming Language :: Python :: 3
Classifier: Programming Language :: Python :: 3 :: Only
Classifier: Topic :: Communications
Classifier: Typing :: Typed
License-File: LICENSE
